Metadata-Version: 1.1
Name: pisarnwatebasiccalculator
Version: 0.0.1
Summary: A very very basic calculator
Home-page: UNKNOWN
Author: Pisarnwate Jitvimol
Author-email: pisarnwate@gmail.com
License: MIT
Keywords: calculator
Platform: UNKNOWN
Classifier: Development Status :: 5 - Production/Stable
Classifier: Intended Audience :: Education
Classifier: Operating System :: Microsoft :: Windows :: Windows 10
Classifier: License :: OSI Approved :: MIT License
Classifier: Programming Language :: Python :: 3
